hunabku_urlshortener/__init__.py
hunabku_urlshortener/_version.py
hunabku_urlshortener/endpoints/Shortener.py
Hunabku_urlshortener-0.0.3.dist-info/METADATA
Hunabku_urlshortener-0.0.3.dist-info/WHEEL
Hunabku_urlshortener-0.0.3.dist-info/top_level.txt
Hunabku_urlshortener-0.0.3.dist-info/RECORD
