Metadata-Version: 2.1
Name: Hunabku-urlshortener
Version: 0.0.3
Summary: Hunabku plguin
Home-page: https://github.com/colav/Hunabku_plugins
Author: Colav
Author-email: colav@udea.edu.co
License: BSD
Requires-Dist: hunabku
Requires-Dist: validators
Requires-Dist: pymongo
Requires-Dist: pybase62
